sockssl/__init__.py
sockssl/certstore.py
sockssl/cli.py
sockssl/factory.py
sockssl/log.py
sockssl/service.py
sockssl/tls_client_hello.py
sockssl/protocol/__init__.py
sockssl/protocol/isocks.py
sockssl/protocol/socks4.py
sockssl/protocol/socks5.py
tests/__init__.py
pysockssl-0.2.dist-info/LICENSE
pysockssl-0.2.dist-info/METADATA
pysockssl-0.2.dist-info/WHEEL
pysockssl-0.2.dist-info/entry_points.txt
pysockssl-0.2.dist-info/top_level.txt
pysockssl-0.2.dist-info/RECORD
