Metadata-Version: 2.1
Name: pysockssl
Version: 0.2
Summary: Simple TCP/TLS mitm engine supports SOCKSv4 + SOCKSv5 + Cert store
Home-page: https://github.com/trichimtrich/pysockssl
Author: trichimtrich
Author-email: trichimtrich@gmail.com
License: GPL v3
Keywords: mitm,proxy,ssl,tls,socksv4,socksv5,socks4,socks5
Platform: UNKNOWN
Classifier: Operating System :: OS Independent
Classifier: Natural Language :: English
Classifier: Programming Language :: Python :: 3 :: Only
Requires-Python: >=3.5
Requires-Dist: twisted
Requires-Dist: kaitaistruct
Requires-Dist: pyOpenSSL
Requires-Dist: service-identity
Requires-Dist: click
